{
  "verifiedImplementationSha": "21622c11e0fd1ae781f718143ce701ce0a13cc4f",
  "implementationTreeSha": "c7ca38f21fdc271b7da93842895e4c6d7e3420ec",
  "evidenceWorktreeBaseSha": "3b36749fb72216d791429fdfdf7b943eaf524d2a",
  "originMainObservedDuringVerification": "3b36749fb72216d791429fdfdf7b943eaf524d2a",
  "verificationWorktree": "C:\\Users\\info\\OneDrive\\Dokument\\SwarmSim-verify-21622c1",
  "primaryDirtyWorkspaceUsed": false,
  "testsRanBeforeEvidenceCommit": true,
  "environment": {
    "nodeVersion": "v24.14.0",
    "npmVersion": "11.9.0",
    "gitCommitEnv": "21622c11e0fd1ae781f718143ce701ce0a13cc4f"
  },
  "evidenceAllowlist": {
    "0.12.0Phase1": [
      "docs/live-logs/browser-test-0.12.0-laboratory-phase1.json",
      "docs/live-logs/browser-test-0.12.0-laboratory-phase1.md",
      "docs/test-data/0.12.0-laboratory/example-result.json",
      "docs/test-data/0.12.0-laboratory/example-result.csv",
      "docs/test-data/0.12.0-laboratory/example-result.md"
    ],
    "0.12.2LiveRunner": [
      "docs/live-logs/browser-test-0.12.2-laboratory-live-runner-final.json",
      "docs/live-logs/browser-test-0.12.2-laboratory-live-runner-final.md",
      "docs/test-data/0.12.2-laboratory/example-copy-summary.txt",
      "docs/test-data/0.12.2-laboratory/example-live-result.csv",
      "docs/test-data/0.12.2-laboratory/example-live-result.json",
      "docs/test-data/0.12.2-laboratory/example-live-result.md"
    ]
  },
  "commandLog": [
    {
      "command": "git fetch origin; git show origin/main:docs/GIT_VERIFICATION_PROTOCOL.md",
      "exitCode": 0,
      "rawSummary": "protocol read from origin/main"
    },
    {
      "command": "git cat-file -e 21622c11e0fd1ae781f718143ce701ce0a13cc4f^{commit}; git worktree add --detach ..\\SwarmSim-verify-21622c1 21622c11e0fd1ae781f718143ce701ce0a13cc4f",
      "exitCode": 0,
      "rawSummary": "detached verification worktree created at exact implementation SHA"
    },
    {
      "command": "git rev-parse --verify HEAD; git rev-parse --verify \"HEAD^{tree}\"; git rev-parse origin/main; git status --short --untracked-files=no",
      "exitCode": 0,
      "rawSummary": "21622c11e0fd1ae781f718143ce701ce0a13cc4f / c7ca38f21fdc271b7da93842895e4c6d7e3420ec / 3b36749fb72216d791429fdfdf7b943eaf524d2a / clean"
    },
    {
      "command": "npm install",
      "exitCode": 0,
      "rawSummary": "added 2 packages, audited 3 packages, found 0 vulnerabilities"
    },
    {
      "command": "git rev-parse HEAD; git rev-parse HEAD^{tree}; node --version; npm --version",
      "exitCode": 0,
      "rawSummary": "21622c11e0fd1ae781f718143ce701ce0a13cc4f / c7ca38f21fdc271b7da93842895e4c6d7e3420ec / v24.14.0 / 11.9.0"
    },
    {
      "command": "npm run build",
      "exitCode": 0,
      "rawSummary": "Canonical userscript already up to date."
    },
    {
      "command": "npm run verify",
      "exitCode": 0,
      "rawSummary": "Build check passed; 0.12.2 LABORATORY LIVE RUNNER VERIFIED; Repo guardrail validation passed"
    },
    {
      "command": "npm run verify:0.12.0:laboratory:phase1",
      "exitCode": 0,
      "rawSummary": "0.12.0 LABORATORY PHASE 1 VERIFIED; runCount: 6"
    },
    {
      "command": "npm run verify:0.12.1:laboratory:live",
      "exitCode": 0,
      "rawSummary": "0.12.2 LABORATORY LIVE RUNNER VERIFIED"
    },
    {
      "command": "npm run verify:0.12.2:laboratory:hom-resolver",
      "exitCode": 0,
      "rawSummary": "0.12.2 LABORATORY LIVE RUNNER VERIFIED"
    },
    {
      "command": "git diff --check",
      "exitCode": 0,
      "rawSummary": "warnings only about CRLF normalization; no whitespace or patch-format errors"
    },
    {
      "command": "git fetch origin; git worktree add -b evidence/exact-sha-21622c1 ..\\SwarmSim-evidence-21622c1 origin/main; git rev-parse HEAD; git rev-parse origin/main; git status --short",
      "exitCode": 0,
      "rawSummary": "evidence worktree created; HEAD and origin/main both 3b36749fb72216d791429fdfdf7b943eaf524d2a"
    }
  ],
  "finalVerificationWorktreeState": {
    "head": "21622c11e0fd1ae781f718143ce701ce0a13cc4f",
    "statusAfterAllCommands": "clean after restoring allowlisted evidence files"
  }
}